allauth_headless_client.py
allauth_headless_client-0.1.0.dist-info/LICENSE
allauth_headless_client-0.1.0.dist-info/WHEEL
allauth_headless_client-0.1.0.dist-info/METADATA
allauth_headless_client-0.1.0.dist-info/RECORD
